aioscpy/VERSION
aioscpy/__init__.py
aioscpy/__main__.py
aioscpy/cmdline.py
aioscpy/crawler.py
aioscpy/exceptions.py
aioscpy/inject.py
aioscpy/logformatter.py
aioscpy/signalmanager.py
aioscpy/signals.py
aioscpy/spider.py
aioscpy/commands/__init__.py
aioscpy/commands/crawl.py
aioscpy/commands/genspider.py
aioscpy/commands/onespider.py
aioscpy/commands/runspider.py
aioscpy/commands/startproject.py
aioscpy/commands/version.py
aioscpy/core/__init__.py
aioscpy/core/engine.py
aioscpy/core/scraper.py
aioscpy/core/downloader/__init__.py
aioscpy/core/downloader/handlers/__init__.py
aioscpy/core/downloader/handlers/aiohttp.py
aioscpy/core/downloader/handlers/curl_cffi.py
aioscpy/core/downloader/handlers/httpx.py
aioscpy/core/downloader/handlers/pyhttpx.py
aioscpy/core/downloader/handlers/requests.py
aioscpy/core/scheduler/__init__.py
aioscpy/core/scheduler/memory.py
aioscpy/core/scheduler/redis.py
aioscpy/http/__init__.py
aioscpy/http/request/__init__.py
aioscpy/http/request/form.py
aioscpy/http/request/json.py
aioscpy/http/response/__init__.py
aioscpy/http/response/text.py
aioscpy/libs/__init__.py
aioscpy/libs/statscollectors.py
aioscpy/libs/downloadermiddlewares/__init__.py
aioscpy/libs/downloadermiddlewares/stats.py
aioscpy/libs/extensions/__init__.py
aioscpy/libs/extensions/corestats.py
aioscpy/libs/extensions/logstats.py
aioscpy/middleware/__init__.py
aioscpy/middleware/adaptive_concurrency.py
aioscpy/middleware/downloader.py
aioscpy/middleware/extension.py
aioscpy/middleware/itempipeline.py
aioscpy/middleware/manager.py
aioscpy/queue/__init__.py
aioscpy/queue/compat.py
aioscpy/queue/convert.py
aioscpy/queue/memory/__init__.py
aioscpy/queue/memory/_queue.py
aioscpy/queue/rabbitmq/__init__.py
aioscpy/queue/rabbitmq/_queue.py
aioscpy/queue/redis/__init__.py
aioscpy/queue/redis/_queue.py
aioscpy/queue/redis/_queue_async.py
aioscpy/settings/__init__.py
aioscpy/settings/default_settings.py
aioscpy/templates/project/__init__.py
aioscpy/templates/project/aioscpy.cfg
aioscpy-0.3.13.dist-info/LICENSE
aioscpy-0.3.13.dist-info/METADATA
aioscpy-0.3.13.dist-info/WHEEL
aioscpy-0.3.13.dist-info/entry_points.txt
aioscpy-0.3.13.dist-info/top_level.txt
aioscpy-0.3.13.dist-info/RECORD
