Metadata-Version: 2.1
Name: aioscpy
Version: 0.3.13
Summary: An asyncio + aiolibs crawler imitate scrapy framework
Home-page: https://github.com/ihandmine/aioscpy
Author: handmine
Author-email: handmine@outlook.com
License: MIT
Keywords: crawler
Classifier: License :: OSI Approved :: MIT License
Classifier: Programming Language :: Python
Classifier: Programming Language :: Python :: 3.7
Classifier: Development Status :: 3 - Alpha
Classifier: Framework :: AsyncIO
Classifier: Operating System :: Unix
Classifier: Operating System :: Microsoft :: Windows
Classifier: Operating System :: MacOS
Requires-Python: >=3.8.0
License-File: LICENSE
Requires-Dist: aiohttp
Requires-Dist: httpx
Requires-Dist: anti-header
Requires-Dist: w3lib
Requires-Dist: parsel
Requires-Dist: PyDispatcher
Requires-Dist: redis
Requires-Dist: anyio
Requires-Dist: ujson
Provides-Extra: aiohttp
Requires-Dist: aiohttp; extra == "aiohttp"
Requires-Dist: cryptography; extra == "aiohttp"
Provides-Extra: all
Requires-Dist: aiohttp; extra == "all"
Requires-Dist: httpx; extra == "all"
Requires-Dist: anti-header; extra == "all"
Requires-Dist: w3lib; extra == "all"
Requires-Dist: parsel; extra == "all"
Requires-Dist: PyDispatcher; extra == "all"
Requires-Dist: redis; extra == "all"
Requires-Dist: anyio; extra == "all"
Requires-Dist: ujson; extra == "all"
Provides-Extra: httpx
Requires-Dist: httpx[http2]>=0.23.0; extra == "httpx"
